repl_python_codestats/__init__.py
repl_python_codestats/_metainfo.py
repl_python_codestats/_version.py
repl_python_codestats/ipython.py
repl_python_codestats/ptpython.py
repl_python_codestats/py.typed
repl_python_codestats/python.py
repl_python_codestats/utils.py
repl_python_codestats-0.0.6.dist-info/LICENSE
repl_python_codestats-0.0.6.dist-info/METADATA
repl_python_codestats-0.0.6.dist-info/WHEEL
repl_python_codestats-0.0.6.dist-info/top_level.txt
repl_python_codestats-0.0.6.dist-info/RECORD
