Metadata-Version: 2.1
Name: repl-python-codestats
Version: 0.0.6
Summary: A codestats plugin for python REPLs
Author-email: Wu Zhenyu <wuzhenyu@ustc.edu>
License: GPL v3
Project-URL: Homepage, https://repl-python-codestats.readthedocs.io
Project-URL: Download, https://github.com/Freed-Wu/repl-python-codestats/releases
Project-URL: Bug Report, https://github.com/Freed-Wu/repl-python-codestats/issues
Project-URL: Source, https://github.com/Freed-Wu/repl-python-codestats
Keywords: codestats,plugin,python,ptpython,ipython
Classifier: Development Status :: 3 - Alpha
Classifier: Intended Audience :: Developers
Classifier: Topic :: Software Development :: Build Tools
Classifier: License :: OSI Approved :: GNU General Public License v3 (GPLv3)
Classifier: Operating System :: Microsoft :: Windows
Classifier: Operating System :: POSIX
Classifier: Operating System :: Unix
Classifier: Operating System :: MacOS
Classifier: Programming Language :: Python :: 3 :: Only
Classifier: Programming Language :: Python :: 3
Classifier: Programming Language :: Python :: 3.9
Classifier: Programming Language :: Python :: 3.10
Classifier: Programming Language :: Python :: 3.11
Classifier: Programming Language :: Python :: Implementation :: CPython
Classifier: Programming Language :: Python :: Implementation :: PyPy
Requires-Python: >=3.9
License-File: LICENSE
Requires-Dist: repl-python-wakatime
Provides-Extra: dev
Requires-Dist: keyring ; extra == 'dev'
Requires-Dist: keyrings.alt ; extra == 'dev'
Requires-Dist: pre-commit ; extra == 'dev'
Requires-Dist: ptpython[ptipython] ; extra == 'dev'
Requires-Dist: pytest-cov ; extra == 'dev'
Provides-Extra: ipython
Requires-Dist: traitlets ; extra == 'ipython'
Provides-Extra: ptipython
Requires-Dist: ptpython[ptipython] ; extra == 'ptipython'
Provides-Extra: ptpython
Requires-Dist: ptpython ; extra == 'ptpython'
